rdcpy/__init__.py
rdcpy/preprocessing/__init__.py
rdcpy/preprocessing/api.py
rdcpy/preprocessing/core.py
rdcpy-0.1.0.dist-info/LICENSE
rdcpy-0.1.0.dist-info/METADATA
rdcpy-0.1.0.dist-info/WHEEL
rdcpy-0.1.0.dist-info/top_level.txt
rdcpy-0.1.0.dist-info/RECORD
