Metadata-Version: 2.1
Name: rdcpy
Version: 0.1.0
Summary: Пакет для работы на платформе НЦСЭД.
Author: Владимирова Алина Валерьевна
Author-email: alina.v.vladimirova@gmail.com
Requires-Python: >=2.7
License-File: LICENSE
Requires-Dist: numpy
Requires-Dist: pandas
Requires-Dist: re
Requires-Dist: IPython
